pymalscraper/__init__.py
pymalscraper/config.py
pymalscraper/models.py
pymalscraper/scraper.py
pymalscraper/shortcuts.py
pymalscraper-3.0.1.dist-info/LICENSE
pymalscraper-3.0.1.dist-info/METADATA
pymalscraper-3.0.1.dist-info/WHEEL
pymalscraper-3.0.1.dist-info/top_level.txt
pymalscraper-3.0.1.dist-info/RECORD
