Metadata-Version: 2.1
Name: pymalscraper
Version: 3.0.1
Summary: Simple Anime Web Scraper.
Home-page: https://github.com/prinsepipo/anime-scraper
Author: prinsepipo
Author-email: prinsepipo.sanchez@gmail.com
License: MIT
Platform: UNKNOWN
Requires-Python: >=3
Requires-Dist: requests
Requires-Dist: BeautifulSoup4
Requires-Dist: lxml
